odoo/addons/web_advanced_search/README.rst
odoo/addons/web_advanced_search/__init__.py
odoo/addons/web_advanced_search/__manifest__.py
odoo/addons/web_advanced_search/i18n/da.po
odoo/addons/web_advanced_search/i18n/de.po
odoo/addons/web_advanced_search/i18n/es.po
odoo/addons/web_advanced_search/i18n/fr.po
odoo/addons/web_advanced_search/i18n/hr.po
odoo/addons/web_advanced_search/i18n/it.po
odoo/addons/web_advanced_search/i18n/nl.po
odoo/addons/web_advanced_search/i18n/nl_NL.po
odoo/addons/web_advanced_search/i18n/pl.po
odoo/addons/web_advanced_search/i18n/pt.po
odoo/addons/web_advanced_search/i18n/pt_BR.po
odoo/addons/web_advanced_search/i18n/tr.po
odoo/addons/web_advanced_search/i18n/web_advanced_search.pot
odoo/addons/web_advanced_search/i18n/zh_CN.po
odoo/addons/web_advanced_search/readme/CONTRIBUTORS.rst
odoo/addons/web_advanced_search/readme/DESCRIPTION.rst
odoo/addons/web_advanced_search/readme/HISTORY.rst
odoo/addons/web_advanced_search/readme/ROADMAP.rst
odoo/addons/web_advanced_search/readme/USAGE.rst
odoo/addons/web_advanced_search/static/description/icon.png
odoo/addons/web_advanced_search/static/description/index.html
odoo/addons/web_advanced_search/static/img/debug_mode.png
odoo/addons/web_advanced_search/static/src/js/DomainSelector.esm.js
odoo/addons/web_advanced_search/static/src/js/RecordPicker.esm.js
odoo/addons/web_advanced_search/static/src/js/dropdown.esm.js
odoo/addons/web_advanced_search/static/src/js/utils.esm.js
odoo/addons/web_advanced_search/static/src/legacy/js/control_panel/advanced_filter_item.esm.js
odoo/addons/web_advanced_search/static/src/legacy/js/control_panel/custom_filter_item.esm.js
odoo/addons/web_advanced_search/static/src/legacy/js/control_panel/filter_menu.esm.js
odoo/addons/web_advanced_search/static/src/search/filter_menu/advanced_filter_item.esm.js
odoo/addons/web_advanced_search/static/src/search/filter_menu/advanced_filter_item.xml
odoo/addons/web_advanced_search/static/src/search/filter_menu/custom_filter_item.esm.js
odoo_addon_web_advanced_search-16.0.1.0.6.4.dist-info/METADATA
odoo_addon_web_advanced_search-16.0.1.0.6.4.dist-info/WHEEL
odoo_addon_web_advanced_search-16.0.1.0.6.4.dist-info/top_level.txt
odoo_addon_web_advanced_search-16.0.1.0.6.4.dist-info/RECORD
